{
  "nhits":15324,
  "parameters":{
    "dataset":[
      "liste_des_prenoms_2004_a_2012"
    ],
    "timezone":"UTC",
    "rows":20,
    "format":"json"
  },
  "records":[
    {
      "datasetid":"liste_des_prenoms_2004_a_2012",
      "recordid":"506ca1095b161fa0c936444d252bbe4447ed7faa",
      "fields":{
        "nombre":54,
        "annee":"2012",
        "prenoms":"Brian",
        "sexe":"M"
      },
      "record_timestamp":"2017-01-06T15:40:05+00:00"
    },
    {
      "datasetid":"liste_des_prenoms_2004_a_2012",
      "recordid":"506ca1095b161fa0c936444d252bbe4447ed7faa",
      "fields":{
        "nombre":345,
        "annee":"2009",
        "prenoms":"Fabrice",
        "sexe":"M"
      },
      "record_timestamp":"2017-01-06T15:40:05+00:00"
    },
    {
      "datasetid":"liste_des_prenoms_2004_a_2012",
      "recordid":"506ca1095b161fa0c936444d252bbe4447ed7faa",
      "fields":{
        "nombre":2,
        "annee":"2009",
        "prenoms":"Kris",
        "sexe":"M"
      },
      "record_timestamp":"2017-01-06T15:40:05+00:00"
    },
    {
      "datasetid":"liste_des_prenoms_2004_a_2012",
      "recordid":"506ca1095b161fa0c936444d252bbe4447ed7faa",
      "fields":{
        "nombre":26,
        "annee":"2012",
        "prenoms":"Carl",
        "sexe":"M"
      },
      "record_timestamp":"2017-01-06T15:40:05+00:00"
    },
    {
      "datasetid":"liste_des_prenoms_2004_a_2012",
      "recordid":"506ca1095b161fa0c936444d252bbe4447ed7faa",
      "fields":{
        "nombre":786,
        "annee":"2009",
        "prenoms":"Marine",
        "sexe":"F"
      },
      "record_timestamp":"2017-01-06T15:40:05+00:00"
    },
    {
      "datasetid":"liste_des_prenoms_2004_a_2012",
      "recordid":"506ca1095b161fa0c936444d252bbe4447ed7faa",
      "fields":{
        "nombre":22,
        "annee":"2009",
        "prenoms":"Paul",
        "sexe":"F"
      },
      "record_timestamp":"2017-01-06T15:40:05+00:00"
    },
    {
      "datasetid":"liste_des_prenoms_2004_a_2012",
      "recordid":"506ca1095b161fa0c936444d252bbe4447ed7faa",
      "fields":{
        "nombre":345,
        "annee":"2009",
        "prenoms":"Liam",
        "sexe":"F"
      },
      "record_timestamp":"2017-01-06T15:40:05+00:00"
    },
    {
      "datasetid":"liste_des_prenoms_2004_a_2012",
      "recordid":"506ca1095b161fa0c936444d252bbe4447ed7faa",
      "fields":{
        "nombre":643,
        "annee":"2009",
        "prenoms":"Melina",
        "sexe":"F"
      },
      "record_timestamp":"2017-01-06T15:40:05+00:00"
    },
    {
      "datasetid":"liste_des_prenoms_2004_a_2012",
      "recordid":"506ca1095b161fa0c936444d252bbe4447ed7faa",
      "fields":{
        "nombre":732,
        "annee":"2015",
        "prenoms":"Celine",
        "sexe":"F"
      },
      "record_timestamp":"2017-01-06T15:40:05+00:00"
    },
    {
      "datasetid":"liste_des_prenoms_2004_a_2012",
      "recordid":"506ca1095b161fa0c936444d252bbe4447ed7faa",
      "fields":{
        "nombre":1000,
        "annee":"2010",
        "prenoms":"Bilal",
        "sexe":"X"
      },
      "record_timestamp":"2017-01-06T15:40:05+00:00"
    },
    {
      "datasetid":"liste_des_prenoms_2004_a_2012",
      "recordid":"506ca1095b161fa0c936444d252bbe4447ed7faa",
      "fields":{
        "nombre":98,
        "annee":"2010",
        "prenoms":"Marc",
        "sexe":"M"
      },
      "record_timestamp":"2017-01-06T15:40:05+00:00"
    },
    {
      "datasetid":"liste_des_prenoms_2004_a_2012",
      "recordid":"506ca1095b161fa0c936444d252bbe4447ed7faa",
      "fields":{
        "nombre":765,
        "annee":"2010",
        "prenoms":"Joy",
        "sexe":"F"
      },
      "record_timestamp":"2017-01-06T15:40:05+00:00"
    },
    {
      "datasetid":"liste_des_prenoms_2004_a_2012",
      "recordid":"506ca1095b161fa0c936444d252bbe4447ed7faa",
      "fields":{
        "nombre":35,
        "annee":"2009",
        "prenoms":"Chloé",
        "sexe":"F"
      },
      "record_timestamp":"2017-01-06T15:40:05+00:00"
    },
    {
      "datasetid":"liste_des_prenoms_2004_a_2012",
      "recordid":"506ca1095b161fa0c936444d252bbe4447ed7faa",
      "fields":{
        "nombre":566,
        "annee":"2010",
        "prenoms":"Elodie",
        "sexe":"F"
      },
      "record_timestamp":"2017-01-06T15:40:05+00:00"
    },
    {
      "datasetid":"liste_des_prenoms_2004_a_2012",
      "recordid":"506ca1095b161fa0c936444d252bbe4447ed7faa",
      "fields":{
        "nombre":22,
        "annee":"2010",
        "prenoms":"Manon",
        "sexe":"F"
      },
      "record_timestamp":"2017-01-06T15:40:05+00:00"
    },
    {
      "datasetid":"liste_des_prenoms_2004_a_2012",
      "recordid":"64a3ed5cea2de48a827e8ee40bace85c322110ef",
      "fields":{
        "nombre":197,
        "annee":"2010",
        "prenoms":"Alexandre",
        "sexe":"X"
      },
      "record_timestamp":"2017-01-06T15:40:05+00:00"
    },
    {
      "datasetid":"liste_des_prenoms_2004_a_2012",
      "recordid":"64a3ed5cea2de48a827e8ee40bace85c322110ef",
      "fields":{
        "nombre":666,
        "annee":"2010",
        "prenoms":"Nadia",
        "sexe":"F"
      },
      "record_timestamp":"2017-01-06T15:40:05+00:00"
    },
    {
      "datasetid":"liste_des_prenoms_2004_a_2012",
      "recordid":"64a3ed5cea2de48a827e8ee40bace85c322110ef",
      "fields":{
        "nombre":197,
        "annee":"2010",
        "prenoms":"Alice",
        "sexe":"X"
      },
      "record_timestamp":"2017-01-06T15:40:05+00:00"
    },
    {
      "datasetid":"liste_des_prenoms_2004_a_2012",
      "recordid":"d2127e5f7622b7ef5f4257f5a5200259c5f5e3b6",
      "fields":{
        "nombre":197,
        "annee":"2016",
        "prenoms":"Victor",
        "sexe":"M"
      },
      "record_timestamp":"2017-01-06T15:40:05+00:00"
    },
    {
      "datasetid":"liste_des_prenoms_2004_a_2012",
      "recordid":"145bc556544f4bf2b3a6297eb0ad980d746e350d",
      "fields":{
        "nombre":129,
        "annee":"2016",
        "prenoms":"Boule",
        "sexe":"M"
      },
      "record_timestamp":"2017-01-06T15:40:05+00:00"
    },
    {
      "datasetid":"liste_des_prenoms_2004_a_2012",
      "recordid":"43f10ad214062782c9d40bfb99fd16fcf3e5383d",
      "fields":{
        "nombre":119,
        "annee":"2016",
        "prenoms":"Lucie",
        "sexe":"F"
      },
      "record_timestamp":"2017-01-06T15:40:05+00:00"
    },
    {
      "datasetid":"liste_des_prenoms_2004_a_2012",
      "recordid":"9dab68e9b5a3e618a8d38be579eaae878d65c909",
      "fields":{
        "nombre":100,
        "annee":"2016",
        "prenoms":"Pauline",
        "sexe":"F"
      },
      "record_timestamp":"2017-01-06T15:40:05+00:00"
    },
    {
      "datasetid":"liste_des_prenoms_2004_a_2012",
      "recordid":"ceb2a69d04d050c2c4eebfb02667dba048edf897",
      "fields":{
        "nombre":94,
        "annee":"2016",
        "prenoms":"Melanie",
        "sexe":"F"
      },
      "record_timestamp":"2017-01-06T15:40:05+00:00"
    },
    {
      "datasetid":"liste_des_prenoms_2004_a_2012",
      "recordid":"75884bbddfbacd10a14cd444250ea0c306fb21e1",
      "fields":{
        "nombre":82,
        "annee":"2016",
        "prenoms":"Baptiste",
        "sexe":"M"
      },
      "record_timestamp":"2017-01-06T15:40:05+00:00"
    },
    {
      "datasetid":"liste_des_prenoms_2004_a_2012",
      "recordid":"d5d78a8f27fa2c08dbcef1821bd6a9984f7b040f",
      "fields":{
        "nombre":79,
        "annee":"2016",
        "prenoms":"Maël",
        "sexe":"M"
      },
      "record_timestamp":"2017-01-06T15:40:05+00:00"
    },
    {
      "datasetid":"liste_des_prenoms_2004_a_2012",
      "recordid":"fdc25e7bf2cb3e46f34f2d7c3ae55fd520abf70c",
      "fields":{
        "nombre":71,
        "annee":"2016",
        "prenoms":"Ibrahim",
        "sexe":"M"
      },
      "record_timestamp":"2017-01-06T15:40:05+00:00"
    },
    {
      "datasetid":"liste_des_prenoms_2004_a_2012",
      "recordid":"9268ef97ece8642ad5342646731d58644c17945c",
      "fields":{
        "nombre":62,
        "annee":"2016",
        "prenoms":"Noemie",
        "sexe":"F"
      },
      "record_timestamp":"2017-01-06T15:40:05+00:00"
    },
    {
      "datasetid":"liste_des_prenoms_2004_a_2012",
      "recordid":"03f09f14cab228c27996d2ac02a0efa649dffaed",
      "fields":{
        "nombre":61,
        "annee":"2016",
        "prenoms":"Nolan",
        "sexe":"M"
      },
      "record_timestamp":"2017-01-06T15:40:05+00:00"
    },
    {
      "datasetid":"liste_des_prenoms_2004_a_2012",
      "recordid":"1536b667adeb8c56be86b950f175be2d59e1ae39",
      "fields":{
        "nombre":59,
        "annee":"2016",
        "prenoms":"Félix",
        "sexe":"M"
      },
      "record_timestamp":"2017-01-06T15:40:05+00:00"
    },
    {
      "datasetid":"liste_des_prenoms_2004_a_2012",
      "recordid":"f2087489f1136ba4f984e54d5eab549ccf909794",
      "fields":{
        "nombre":49,
        "annee":"2016",
        "prenoms":"Léonard",
        "sexe":"M"
      },
      "record_timestamp":"2017-01-06T15:40:05+00:00"
    },
    {
      "datasetid":"liste_des_prenoms_2004_a_2012",
      "recordid":"d930a84ffe1a7645967aed94c8fab7c460009875",
      "fields":{
        "nombre":45,
        "annee":"2016",
        "prenoms":"Anatole",
        "sexe":"M"
      },
      "record_timestamp":"2017-01-06T15:40:05+00:00"
    },
    {
      "datasetid":"liste_des_prenoms_2004_a_2012",
      "recordid":"ad4d0f27975b231fc850dcfa707d4397b0d46007",
      "fields":{
        "nombre":44,
        "annee":"2016",
        "prenoms":"Isabelle",
        "sexe":"F"
      },
      "record_timestamp":"2017-01-06T15:40:05+00:00"
    },
    {
      "datasetid":"liste_des_prenoms_2004_a_2012",
      "recordid":"660be3959d32f5dea3804ea7110987e0028812a6",
      "fields":{
        "nombre":40,
        "annee":"2016",
        "prenoms":"Henrietta",
        "sexe":"F"
      },
      "record_timestamp":"2017-01-06T15:40:05+00:00"
    },
    {
      "datasetid":"liste_des_prenoms_2004_a_2012",
      "recordid":"4b1146bf058cc30a008d1faa573e80aa5f005314",
      "fields":{
        "nombre":36,
        "annee":"2016",
        "prenoms":"Hadrien",
        "sexe":"M"
      },
      "record_timestamp":"2017-01-06T15:40:05+00:00"
    },
    {
      "datasetid":"liste_des_prenoms_2004_a_2012",
      "recordid":"962b985064876dc83f31933840c4b4d262367680",
      "fields":{
        "nombre":35,
        "annee":"2016",
        "prenoms":"Catherine",
        "sexe":"F"
      },
      "record_timestamp":"2017-01-06T15:40:05+00:00"
    },
    {
      "datasetid":"liste_des_prenoms_2004_a_2012",
      "recordid":"806dec3f78c37a0247d2146f29bbf1d10359fbfe",
      "fields":{
        "nombre":31,
        "annee":"2016",
        "prenoms":"Claire",
        "sexe":"F"
      },
      "record_timestamp":"2017-01-06T15:40:05+00:00"
    },
    {
      "datasetid":"liste_des_prenoms_2004_a_2012",
      "recordid":"806dec3f78c37a0247d2146f29bbf1d10359fbfe",
      "fields":{
        "nombre":88,
        "annee":"2011",
        "prenoms":"Claire",
        "sexe":"F"
      },
      "record_timestamp":"2017-01-06T15:40:05+00:00"
    },
    {
      "datasetid":"liste_des_prenoms_2004_a_2012",
      "recordid":"806dec3f78c37a0247d2146f29bbf1d10359fbfe",
      "fields":{
        "nombre":31,
        "annee":"2011",
        "prenoms":"Harold",
        "sexe":"M"
      },
      "record_timestamp":"2017-01-06T15:40:05+00:00"
    },
    {
      "datasetid":"liste_des_prenoms_2004_a_2012",
      "recordid":"806dec3f78c37a0247d2146f29bbf1d10359fbfe",
      "fields":{
        "nombre":123,
        "annee":"2012",
        "prenoms":"Etienne",
        "sexe":"M"
      },
      "record_timestamp":"2017-01-06T15:40:05+00:00"
    },
    {
      "datasetid":"liste_des_prenoms_2004_a_2012",
      "recordid":"806dec3f78c37a0247d2146f29bbf1d10359fbfe",
      "fields":{
        "nombre":32,
        "annee":"2009",
        "prenoms":"Brandon",
        "sexe":"M"
      },
      "record_timestamp":"2017-01-06T15:40:05+00:00"
    },
    {
      "datasetid":"liste_des_prenoms_2004_a_2012",
      "recordid":"806dec3f78c37a0247d2146f29bbf1d10359fbfe",
      "fields":{
        "nombre":999,
        "annee":"2010",
        "prenoms":"Brandon",
        "sexe":"M"
      },
      "record_timestamp":"2017-01-06T15:40:05+00:00"
    },
    {
      "datasetid":"liste_des_prenoms_2004_a_2012",
      "recordid":"806dec3f78c37a0247d2146f29bbf1d10359fbfe",
      "fields":{
        "nombre":99,
        "annee":"2011",
        "prenoms":"Brandon",
        "sexe":"M"
      },
      "record_timestamp":"2017-01-06T15:40:05+00:00"
    },
    {
      "datasetid":"liste_des_prenoms_2004_a_2012",
      "recordid":"806dec3f78c37a0247d2146f29bbf1d10359fbfe",
      "fields":{
        "nombre":85,
        "annee":"2011",
        "prenoms":"Malik",
        "sexe":"M"
      },
      "record_timestamp":"2017-01-06T15:40:05+00:00"
    },
    {
      "datasetid":"liste_des_prenoms_2004_a_2012",
      "recordid":"806dec3f78c37a0247d2146f29bbf1d10359fbfe",
      "fields":{
        "nombre":875,
        "annee":"2012",
        "prenoms":"Nanti",
        "sexe":"M"
      },
      "record_timestamp":"2017-01-06T15:40:05+00:00"
    },
    {
      "datasetid":"liste_des_prenoms_2004_a_2012",
      "recordid":"806dec3f78c37a0247d2146f29bbf1d10359fbfe",
      "fields":{
        "nombre":875,
        "annee":"2012",
        "prenoms":"Leo",
        "sexe":"M"
      },
      "record_timestamp":"2017-01-06T15:40:05+00:00"
    },
    {
      "datasetid":"liste_des_prenoms_2004_a_2012",
      "recordid":"806dec3f78c37a0247d2146f29bbf1d10359fbfe",
      "fields":{
        "nombre":99,
        "annee":"2012",
        "prenoms":"Brandon",
        "sexe":"M"
      },
      "record_timestamp":"2017-01-06T15:40:05+00:00"
    },
    {
      "datasetid":"liste_des_prenoms_2004_a_2012",
      "recordid":"806dec3f78c37a0247d2146f29bbf1d10359fbfe",
      "fields":{
        "nombre":56,
        "annee":"2013",
        "prenoms":"Brandon",
        "sexe":"M"
      },
      "record_timestamp":"2017-01-06T15:40:05+00:00"
    },
    {
      "datasetid":"liste_des_prenoms_2004_a_2012",
      "recordid":"806dec3f78c37a0247d2146f29bbf1d10359fbfe",
      "fields":{
        "nombre":99,
        "annee":"2014",
        "prenoms":"Brandon",
        "sexe":"M"
      },
      "record_timestamp":"2017-01-06T15:40:05+00:00"
    },
    {
      "datasetid":"liste_des_prenoms_2004_a_2012",
      "recordid":"806dec3f78c37a0247d2146f29bbf1d10359fbfe",
      "fields":{
        "nombre":87,
        "annee":"2015",
        "prenoms":"Brandon",
        "sexe":"M"
      },
      "record_timestamp":"2017-01-06T15:40:05+00:00"
    },
    {
      "datasetid":"liste_des_prenoms_2004_a_2012",
      "recordid":"806dec3f78c37a0247d2146f29bbf1d10359fbfe",
      "fields":{
        "nombre":99,
        "annee":"2016",
        "prenoms":"Brandon",
        "sexe":"M"
      },
      "record_timestamp":"2017-01-06T15:40:05+00:00"
    },
    {
      "datasetid":"liste_des_prenoms_2004_a_2012",
      "recordid":"806dec3f78c37a0247d2146f29bbf1d10359fbfe",
      "fields":{
        "nombre":31,
        "annee":"2011",
        "prenoms":"Vlad",
        "sexe":"M"
      },
      "record_timestamp":"2017-01-06T15:40:05+00:00"
    },
    {
      "datasetid":"liste_des_prenoms_2004_a_2012",
      "recordid":"806dec3f78c37a0247d2146f29bbf1d10359fbfe",
      "fields":{
        "nombre":654,
        "annee":"2013",
        "prenoms":"Paula",
        "sexe":"F"
      },
      "record_timestamp":"2017-01-06T15:40:05+00:00"
    },
    {
      "datasetid":"liste_des_prenoms_2004_a_2012",
      "recordid":"806dec3f78c37a0247d2146f29bbf1d10359fbfe",
      "fields":{
        "nombre":43,
        "annee":"2013",
        "prenoms":"Sakris",
        "sexe":"M"
      },
      "record_timestamp":"2017-01-06T15:40:05+00:00"
    },
    {
      "datasetid":"liste_des_prenoms_2004_a_2012",
      "recordid":"806dec3f78c37a0247d2146f29bbf1d10359fbfe",
      "fields":{
        "nombre":3,
        "annee":"2013",
        "prenoms":"Damien",
        "sexe":"M"
      },
      "record_timestamp":"2017-01-06T15:40:05+00:00"
    },
    {
      "datasetid":"liste_des_prenoms_2004_a_2012",
      "recordid":"806dec3f78c37a0247d2146f29bbf1d10359fbfe",
      "fields":{
        "nombre":98,
        "annee":"2013",
        "prenoms":"Paula",
        "sexe":"F"
      },
      "record_timestamp":"2017-01-06T15:40:05+00:00"
    },
    {
      "datasetid":"liste_des_prenoms_2004_a_2012",
      "recordid":"806dec3f78c37a0247d2146f29bbf1d10359fbfe",
      "fields":{
        "nombre":20,
        "annee":"2016",
        "prenoms":"Michelle",
        "sexe":"F"
      },
      "record_timestamp":"2017-01-06T15:40:05+00:00"
    },
    {
      "datasetid":"liste_des_prenoms_2004_a_2012",
      "recordid":"806dec3f78c37a0247d2146f29bbf1d10359fbfe",
      "fields":{
        "nombre":10,
        "annee":"2016",
        "prenoms":"Nadine",
        "sexe":"F"
      },
      "record_timestamp":"2017-01-06T15:40:05+00:00"
    },
    {
      "datasetid":"liste_des_prenoms_2004_a_2012",
      "recordid":"806dec3f78c37a0247d2146f29bbf1d10359fbfe",
      "fields":{
        "nombre":12,
        "annee":"2016",
        "prenoms":"Mariane",
        "sexe":"F"
      },
      "record_timestamp":"2017-01-06T15:40:05+00:00"
    },
    {
      "datasetid":"liste_des_prenoms_2004_a_2012",
      "recordid":"806dec3f78c37a0247d2146f29bbf1d10359fbfe",
      "fields":{
        "nombre":1,
        "annee":"2016",
        "prenoms":"Pierra",
        "sexe":"F"
      },
      "record_timestamp":"2017-01-06T15:40:05+00:00"
    }
  ]
}
